{
	"SpawnForced" : true,
	"SpawnWorld" : "world",
	"SpawnX" : 0,
	"SpawnY" : 61,
	"SpawnZ" : 0,
	"air" : 283,
	"enchantmentSeed" : 3147435581,
	"enderchestinventory" : 
	[
		{
			"ID" : -1
		},
		{
			"ID" : -1
		},
		{
			"ID" : -1
		},
		{
			"ID" : -1
		},
		{
			"ID" : -1
		},
		{
			"ID" : -1
		},
		{
			"ID" : -1
		},
		{
			"ID" : -1
		},
		{
			"ID" : -1
		},
		{
			"ID" : -1
		},
		{
			"ID" : -1
		},
		{
			"ID" : -1
		},
		{
			"ID" : -1
		},
		{
			"ID" : -1
		},
		{
			"ID" : -1
		},
		{
			"ID" : -1
		},
		{
			"ID" : -1
		},
		{
			"ID" : -1
		},
		{
			"ID" : -1
		},
		{
			"ID" : -1
		},
		{
			"ID" : -1
		},
		{
			"ID" : -1
		},
		{
			"ID" : -1
		},
		{
			"ID" : -1
		},
		{
			"ID" : -1
		},
		{
			"ID" : -1
		},
		{
			"ID" : -1
		}
	],
	"equippedItemSlot" : 0,
	"food" : 20,
	"foodExhaustion" : 0.59549999999999859,
	"foodSaturation" : 5.0,
	"foodTickTimer" : 7,
	"gamemode" : -1,
	"health" : 20.0,
	"inventory" : 
	[
		{
			"ID" : -1
		},
		{
			"ID" : -1
		},
		{
			"ID" : -1
		},
		{
			"ID" : -1
		},
		{
			"ID" : -1
		},
		{
			"ID" : -1
		},
		{
			"ID" : -1
		},
		{
			"ID" : -1
		},
		{
			"ID" : -1
		},
		{
			"ID" : -1
		},
		{
			"ID" : -1
		},
		{
			"ID" : -1
		},
		{
			"ID" : -1
		},
		{
			"ID" : -1
		},
		{
			"ID" : -1
		},
		{
			"ID" : -1
		},
		{
			"ID" : -1
		},
		{
			"ID" : -1
		},
		{
			"ID" : -1
		},
		{
			"ID" : -1
		},
		{
			"ID" : -1
		},
		{
			"ID" : -1
		},
		{
			"ID" : -1
		},
		{
			"ID" : -1
		},
		{
			"ID" : -1
		},
		{
			"ID" : -1
		},
		{
			"ID" : -1
		},
		{
			"ID" : -1
		},
		{
			"ID" : -1
		},
		{
			"ID" : -1
		},
		{
			"ID" : -1
		},
		{
			"ID" : -1
		},
		{
			"ID" : -1
		},
		{
			"ID" : -1
		},
		{
			"ID" : -1
		},
		{
			"ID" : -1
		},
		{
			"ID" : -1
		},
		{
			"ID" : -1
		},
		{
			"ID" : -1
		},
		{
			"ID" : -1
		},
		{
			"ID" : -1
		},
		{
			"ID" : -1
		},
		{
			"ID" : -1
		},
		{
			"ID" : -1
		},
		{
			"ID" : -1
		},
		{
			"ID" : -1
		}
	],
	"isflying" : false,
	"knownItems" : null,
	"knownRecipes" : null,
	"lastknownname" : "733402",
	"position" : 
	[
		-3.0853929477439008,
		58.595218521185174,
		4.9884844955077243
	],
	"rotation" : 
	[
		164.99998474121094,
		-13.200000762939453,
		0.0
	],
	"world" : "world",
	"xpCurrent" : 0,
	"xpTotal" : 0
}