{
	"SpawnForced" : true,
	"SpawnWorld" : "world",
	"SpawnX" : 0,
	"SpawnY" : 61,
	"SpawnZ" : 0,
	"air" : 300,
	"enchantmentSeed" : 3189300831,
	"enderchestinventory" : 
	[
		{
			"ID" : -1
		},
		{
			"ID" : -1
		},
		{
			"ID" : -1
		},
		{
			"ID" : -1
		},
		{
			"ID" : -1
		},
		{
			"ID" : -1
		},
		{
			"ID" : -1
		},
		{
			"ID" : -1
		},
		{
			"ID" : -1
		},
		{
			"ID" : -1
		},
		{
			"ID" : -1
		},
		{
			"ID" : -1
		},
		{
			"ID" : -1
		},
		{
			"ID" : -1
		},
		{
			"ID" : -1
		},
		{
			"ID" : -1
		},
		{
			"ID" : -1
		},
		{
			"ID" : -1
		},
		{
			"ID" : -1
		},
		{
			"ID" : -1
		},
		{
			"ID" : -1
		},
		{
			"ID" : -1
		},
		{
			"ID" : -1
		},
		{
			"ID" : -1
		},
		{
			"ID" : -1
		},
		{
			"ID" : -1
		},
		{
			"ID" : -1
		}
	],
	"equippedItemSlot" : 0,
	"food" : 20,
	"foodExhaustion" : 1.648049999999998,
	"foodSaturation" : 5.0,
	"foodTickTimer" : 43,
	"gamemode" : -1,
	"health" : 20.0,
	"inventory" : 
	[
		{
			"ID" : -1
		},
		{
			"ID" : -1
		},
		{
			"ID" : -1
		},
		{
			"ID" : -1
		},
		{
			"ID" : -1
		},
		{
			"ID" : -1
		},
		{
			"ID" : -1
		},
		{
			"ID" : -1
		},
		{
			"ID" : -1
		},
		{
			"ID" : -1
		},
		{
			"ID" : -1
		},
		{
			"ID" : -1
		},
		{
			"ID" : -1
		},
		{
			"ID" : -1
		},
		{
			"ID" : -1
		},
		{
			"ID" : -1
		},
		{
			"ID" : -1
		},
		{
			"ID" : -1
		},
		{
			"ID" : -1
		},
		{
			"ID" : -1
		},
		{
			"ID" : -1
		},
		{
			"ID" : -1
		},
		{
			"ID" : -1
		},
		{
			"ID" : -1
		},
		{
			"ID" : -1
		},
		{
			"ID" : -1
		},
		{
			"ID" : -1
		},
		{
			"ID" : -1
		},
		{
			"ID" : -1
		},
		{
			"ID" : -1
		},
		{
			"ID" : -1
		},
		{
			"ID" : -1
		},
		{
			"ID" : -1
		},
		{
			"ID" : -1
		},
		{
			"ID" : -1
		},
		{
			"ID" : -1
		},
		{
			"ID" : -1
		},
		{
			"ID" : -1
		},
		{
			"ID" : -1
		},
		{
			"ID" : -1
		},
		{
			"ID" : -1
		},
		{
			"ID" : -1
		},
		{
			"ID" : -1
		},
		{
			"ID" : -1
		},
		{
			"ID" : -1
		},
		{
			"ID" : -1
		}
	],
	"isflying" : false,
	"knownItems" : null,
	"knownRecipes" : null,
	"lastknownname" : "AKDHF",
	"position" : 
	[
		4.2966751241368826,
		65.0,
		29.019073985811289
	],
	"rotation" : 
	[
		-114.45001220703125,
		46.350002288818359,
		0.0
	],
	"world" : "world",
	"xpCurrent" : 0,
	"xpTotal" : 0
}